xil-0.4.0.dist-info/METADATA
xil-0.4.0.dist-info/WHEEL
xil-0.4.0.dist-info/entry_points.txt
xil-0.4.0.dist-info/licenses/LICENSE
xil/__init__.py
xil/_currencies.py
xil/_df_normalizer.py
xil/_headers.py
xil/_version.py
xil/boi.py
xil/discount.py
xil/fibi.py
xil/jerusalem.py
xil/leumi.py
xil/massad.py
xil/mercantile.py
xil/mizrahi_tefahot.py
xil/onezero.py
xil/poalim.py
xil/py.typed
xil-0.4.0.dist-info/RECORD
