Metadata-Version: 2.1
Name: xil
Version: 0.4.0
Summary: A Python library for fetching Israeli banks' ILS exchange rates
Keywords: foreign exchange,Israeli banks,Shekel,finance
Author-Email: Jonathan Daniel <jonathand655@gmail.com>
License: MIT
Classifier: Development Status :: 3 - Alpha
Classifier: Intended Audience :: Developers
Classifier: Intended Audience :: Financial and Insurance Industry
Classifier: Intended Audience :: Information Technology
Classifier: Natural Language :: English
Classifier: Natural Language :: Hebrew
Classifier: Operating System :: OS Independent
Classifier: Programming Language :: Python :: 3.12
Classifier: Topic :: Internet :: WWW/HTTP :: Dynamic Content
Classifier: Topic :: Office/Business :: Financial
Classifier: Topic :: Software Development :: Libraries :: Python Modules
Classifier: Typing :: Typed
Project-URL: Repository, https://github.com/jond01/xil
Project-URL: Documentation, https://github.com/jond01/xil#readme
Project-URL: Bug Tracker, https://github.com/jond01/xil/issues
Requires-Python: >=3.12
Requires-Dist: pandas[html]>=2.2.2
